tr4der/__init__.py
tr4der/tr4der.py
tr4der/strategies/__init__.py
tr4der/strategies/machine_learning_strategies.py
tr4der/strategies/simple_strategies.py
tr4der/strategies/technical_strategies.py
tr4der/utils/__init__.py
tr4der/utils/config.py
tr4der/utils/data_loader.py
tr4der/utils/gpt_helper.py
tr4der/utils/metrics.py
tr4der/utils/plot.py
tr4der/utils/type_transformation.py
Tr4der-1.1.0.dist-info/METADATA
Tr4der-1.1.0.dist-info/WHEEL
Tr4der-1.1.0.dist-info/top_level.txt
Tr4der-1.1.0.dist-info/RECORD
