Metadata-Version: 2.1
Name: Tr4der
Version: 1.1.0
Summary: Tr4der is a algorithmic trading library for quantitative strategy ideation.
Home-page: https://github.com/smullins998/tr4der
Author: Sean Mullins
Author-email: smullins998@gmail.com
Classifier: Programming Language :: Python :: 3
Classifier: License :: OSI Approved :: MIT License
Classifier: Operating System :: OS Independent
Requires-Python: >=3.8
Requires-Dist: matplotlib
Requires-Dist: numpy
Requires-Dist: openai (<2.0.0,>=1.0.0)
Requires-Dist: pandas
Requires-Dist: PyYAML
Requires-Dist: seaborn
Requires-Dist: yfinance
Requires-Dist: tensorflow
Requires-Dist: scikit-learn
Requires-Dist: setuptools (>=65.6.3)
